pyrilog/__init__.py
pyrilog/pyrilog.py
pyrilog-0.2.4.dist-info/METADATA
pyrilog-0.2.4.dist-info/WHEEL
pyrilog-0.2.4.dist-info/licenses/LICENSE
pyrilog-0.2.4.dist-info/RECORD
