Metadata-Version: 2.4
Name: pyrilog
Version: 0.2.4
Summary: A Python-based SystemVerilog code generator using context managers
Project-URL: Homepage, https://github.com/nightwatcher/pyrilog
Project-URL: Repository, https://github.com/nightwatcher/pyrilog.git
Project-URL: Issues, https://github.com/nightwatcher/pyrilog/issues
Author-email: NightWatcher <hitszzzf@gmail.com>
License: MIT
License-File: LICENSE
Keywords: code-generation,hardware,hdl,systemverilog,verilog
Classifier: Development Status :: 3 - Alpha
Classifier: Intended Audience :: Developers
Classifier: License :: OSI Approved :: MIT License
Classifier: Programming Language :: Python :: 3
Classifier: Programming Language :: Python :: 3.8
Classifier: Programming Language :: Python :: 3.9
Classifier: Programming Language :: Python :: 3.10
Classifier: Programming Language :: Python :: 3.11
Classifier: Programming Language :: Python :: 3.12
Classifier: Topic :: Scientific/Engineering :: Electronic Design Automation (EDA)
Requires-Python: >=3.8
Provides-Extra: dev
Requires-Dist: black>=22.0; extra == 'dev'
Requires-Dist: build>=0.10.0; extra == 'dev'
Requires-Dist: pytest>=7.0; extra == 'dev'
Requires-Dist: ruff>=0.1.0; extra == 'dev'
Provides-Extra: test
Requires-Dist: pytest>=7.0; extra == 'test'
